bonsai/ldapdn.py
bonsai/ldapclient.py
bonsai/ldapconnection.py
bonsai/ldapvaluelist.py
bonsai/ldapreference.py
bonsai/__init__.py
bonsai/ldapentry.py
bonsai/_bonsai.cpython-312-darwin.so
bonsai/utils.py
bonsai/ldif.py
bonsai/py.typed
bonsai/errors.py
bonsai/ldapurl.py
bonsai/pool.py
bonsai/trio/__init__.py
bonsai/trio/trioconnection.py
bonsai/gevent/geventconnection.py
bonsai/gevent/__init__.py
bonsai/.dylibs/libldap.2.dylib
bonsai/.dylibs/libssl.3.dylib
bonsai/.dylibs/libcrypto.3.dylib
bonsai/.dylibs/liblber.2.dylib
bonsai/tornado/__init__.py
bonsai/tornado/tornadoconnection.py
bonsai/active_directory/__init__.py
bonsai/active_directory/acl.py
bonsai/active_directory/sid.py
bonsai/asyncio/aioconnection.py
bonsai/asyncio/__init__.py
bonsai/asyncio/aiopool.py
bonsai-1.5.3.dist-info/RECORD
bonsai-1.5.3.dist-info/LICENSE
bonsai-1.5.3.dist-info/WHEEL
bonsai-1.5.3.dist-info/top_level.txt
bonsai-1.5.3.dist-info/METADATA
