Metadata-Version: 2.1
Name: bonsai
Version: 1.5.3
Summary: Python 3 module for accessing LDAP directory servers.
Home-page: https://github.com/noirello/bonsai
Author: noirello
Author-email: noirello@gmail.com
License: MIT
Keywords: python3,ldap,ldap3,python-ldap,libldap,winldap,asyncio,gevent,tornado,trio
Classifier: Development Status :: 5 - Production/Stable
Classifier: Intended Audience :: Developers
Classifier: Intended Audience :: System Administrators
Classifier: License :: OSI Approved :: MIT License
Classifier: Operating System :: Microsoft :: Windows
Classifier: Operating System :: Unix
Classifier: Programming Language :: C
Classifier: Programming Language :: Python :: 3 :: Only
Classifier: Programming Language :: Python :: 3.7
Classifier: Programming Language :: Python :: 3.8
Classifier: Programming Language :: Python :: 3.9
Classifier: Programming Language :: Python :: 3.10
Classifier: Programming Language :: Python :: 3.11
Classifier: Programming Language :: Python :: 3.12
Classifier: Programming Language :: Python :: Implementation :: CPython
Classifier: Topic :: Software Development :: Libraries :: Python Modules
Classifier: Topic :: System :: Systems Administration :: Authentication/Directory :: LDAP
License-File: LICENSE
Requires-Dist: typing-extensions >=4.0.0 ; python_version < "3.8"
Provides-Extra: gevent
Requires-Dist: gevent >=1.4.0 ; extra == 'gevent'
Provides-Extra: tornado
Requires-Dist: tornado >=5.1.1 ; extra == 'tornado'
Provides-Extra: trio
Requires-Dist: trio >=0.16.0 ; extra == 'trio'
